adafruit_rp1pio.cpython-311-aarch64-linux-gnu.so
Adafruit_Blinka_Raspberry_Pi5_rp1pio-1.0.0rc0.dist-info/LICENSE
Adafruit_Blinka_Raspberry_Pi5_rp1pio-1.0.0rc0.dist-info/WHEEL
Adafruit_Blinka_Raspberry_Pi5_rp1pio-1.0.0rc0.dist-info/RECORD
Adafruit_Blinka_Raspberry_Pi5_rp1pio-1.0.0rc0.dist-info/top_level.txt
Adafruit_Blinka_Raspberry_Pi5_rp1pio-1.0.0rc0.dist-info/METADATA
