Metadata-Version: 2.2
Name: Adafruit-Blinka-Raspberry-Pi5-rp1pio
Version: 1.0.0rc0
Summary: Control the PIO peripheral on a Raspberry Pi 5
Home-page: https://github.com/adafruit/Adafruit_Blinka_Raspberry_Pi5_rp1pio
Requires-Python: >=3.11
License-File: LICENSE
Provides-Extra: docs
Requires-Dist: myst-parser; extra == "docs"
Requires-Dist: setuptools-scm; extra == "docs"
Requires-Dist: sphinx; extra == "docs"
Requires-Dist: sphinx-rtd-theme; extra == "docs"
Requires-Dist: sphinxcontrib-jquery; extra == "docs"
Dynamic: description
Dynamic: home-page
Dynamic: provides-extra
Dynamic: requires-python
Dynamic: summary
